ckplotlib/__init__.py
ckplotlib/_version.py
ckplotlib/ckplot.py
ckplotlib/color.py
ckplotlib/cycle.py
ckplotlib/savecsv.py
ckplotlib/savefig.py
ckplotlib/ticker.py
ckplotlib/tool.py
ckplotlib/config/__init__.py
ckplotlib/config/config.ini
ckplotlib/mplstyle/__init__.py
ckplotlib/mplstyle/base.mplstyle
ckplotlib/mplstyle/rectangle.mplstyle
ckplotlib/mplstyle/font/arial.mplstyle
ckplotlib/mplstyle/font/times.mplstyle
ckplotlib-1.0.0.dist-info/LICENSE
ckplotlib-1.0.0.dist-info/METADATA
ckplotlib-1.0.0.dist-info/WHEEL
ckplotlib-1.0.0.dist-info/top_level.txt
ckplotlib-1.0.0.dist-info/RECORD
